[
  [
    {
      "chapters": 77,
      "countries": 30,
      "city": 77,
      "members": 54568,
      "past_events": 4742,
      "upcoming_events": 43,
      "avgchapter": 2,
      "avgevent": 61,
      "avgmember": 708,
      "last_update": "Wed Apr  8 14:45:27 2020"
    }
  ],
  [
    {
      "latinAm": 9,
      "us_can": 30,
      "eur": 20,
      "afr": 4,
      "asia": 10,
      "aus": 4,
      "latinAm_m": 5323,
      "us_can_m": 28555,
      "eur_m": 12821,
      "afr_m": 2459,
      "asia_m": 3922,
      "aus_m": 1488
    }
  ]
]
